pytest_cython/__init__.py
pytest_cython/plugin.py
pytest_cython-0.3.1.dist-info/LICENSE.md
pytest_cython-0.3.1.dist-info/METADATA
pytest_cython-0.3.1.dist-info/WHEEL
pytest_cython-0.3.1.dist-info/entry_points.txt
pytest_cython-0.3.1.dist-info/top_level.txt
pytest_cython-0.3.1.dist-info/RECORD
